sigma/backends/khulnasoft/__init__.py
sigma/backends/khulnasoft/khulnasoft.py
sigma/pipelines/khulnasoft/__init__.py
sigma/pipelines/khulnasoft/khulnasoft.py
pysigma_backend_khulnasoft-0.1.0.dist-info/LICENSE
pysigma_backend_khulnasoft-0.1.0.dist-info/METADATA
pysigma_backend_khulnasoft-0.1.0.dist-info/WHEEL
pysigma_backend_khulnasoft-0.1.0.dist-info/RECORD
