Metadata-Version: 2.1
Name: pysigma-backend-khulnasoft
Version: 0.1.0
Summary: pySigma KhulnaSoft backend
Home-page: https://github.com/khulnasoft/pySigma-backend-khulnasoft
License: LGPL-2.1-only
Author: NxPKG
Author-email: 116948796+NxPKG@users.noreply.github.com
Requires-Python: >=3.8,<4.0
Classifier: License :: OSI Approved
Classifier: Programming Language :: Python :: 3
Classifier: Programming Language :: Python :: 3.8
Classifier: Programming Language :: Python :: 3.9
Classifier: Programming Language :: Python :: 3.10
Classifier: Programming Language :: Python :: 3.11
Classifier: Programming Language :: Python :: 3.12
Requires-Dist: pySigma (>=0.11.1,<0.12.0)
Project-URL: Repository, https://github.com/khulnasoft/pySigma-backend-khulnasoft
